{
  "lastUpdated": "2025-08-28T00:00:22.529Z",
  "stats": {
    "users": {
      "count": 93752,
      "change": 0.2
    },
    "revenue": {
      "amount": 376325,
      "change": 4.1
    },
    "projects": {
      "count": 370,
      "change": 0.5
    },
    "tasks": {
      "count": 2859,
      "change": -2.3
    }
  },
  "activities": [
    {
      "type": "user",
      "title": "System alert",
      "timestamp": "2025-08-28T00:00:22.529Z"
    },
    {
      "type": "message",
      "title": "New message",
      "timestamp": "2025-08-27T00:00:20.252Z"
    },
    {
      "type": "message",
      "title": "New message",
      "timestamp": "2025-08-26T00:00:29.132Z"
    },
    {
      "type": "project",
      "title": "User updated profile",
      "timestamp": "2025-08-25T00:00:26.739Z"
    },
    {
      "type": "user",
      "title": "User updated profile",
      "timestamp": "2025-08-24T00:01:01.058Z"
    }
  ],
  "weeklyActivity": [
    {
      "day": "Mon",
      "value": 23
    },
    {
      "day": "Tue",
      "value": 10
    },
    {
      "day": "Wed",
      "value": 73
    },
    {
      "day": "Thu",
      "value": 10
    },
    {
      "day": "Fri",
      "value": 23
    },
    {
      "day": "Sat",
      "value": 97
    },
    {
      "day": "Sun",
      "value": 35
    }
  ],
  "performanceMetrics": [
    {
      "date": "2023-11-18",
      "value": 39
    },
    {
      "date": "2023-11-19",
      "value": 39
    },
    {
      "date": "2023-11-20",
      "value": 12
    },
    {
      "date": "2023-11-21",
      "value": 21
    },
    {
      "date": "2023-11-22",
      "value": 31
    },
    {
      "date": "2023-11-23",
      "value": 22
    },
    {
      "date": "2023-11-24",
      "value": 38
    }
  ]
}