{
  "lastUpdated": "2025-06-17T00:00:55.676Z",
  "stats": {
    "users": {
      "count": 18164,
      "change": -1.2
    },
    "revenue": {
      "amount": 140708,
      "change": 3.5
    },
    "projects": {
      "count": 355,
      "change": 0.3
    },
    "tasks": {
      "count": 1795,
      "change": 16.2
    }
  },
  "activities": [
    {
      "type": "task",
      "title": "Invoice generated",
      "timestamp": "2025-06-17T00:00:55.676Z"
    },
    {
      "type": "payment",
      "title": "Task assigned",
      "timestamp": "2025-06-16T00:00:44.358Z"
    },
    {
      "type": "alert",
      "title": "Project created",
      "timestamp": "2025-06-15T00:00:43.724Z"
    },
    {
      "type": "message",
      "title": "Project milestone reached",
      "timestamp": "2025-06-14T00:00:46.281Z"
    },
    {
      "type": "project",
      "title": "New user registered",
      "timestamp": "2025-06-13T00:00:42.809Z"
    }
  ],
  "weeklyActivity": [
    {
      "day": "Mon",
      "value": 14
    },
    {
      "day": "Tue",
      "value": 15
    },
    {
      "day": "Wed",
      "value": 74
    },
    {
      "day": "Thu",
      "value": 59
    },
    {
      "day": "Fri",
      "value": 88
    },
    {
      "day": "Sat",
      "value": 100
    },
    {
      "day": "Sun",
      "value": 57
    }
  ],
  "performanceMetrics": [
    {
      "date": "2023-09-07",
      "value": 17
    },
    {
      "date": "2023-09-08",
      "value": 47
    },
    {
      "date": "2023-09-09",
      "value": 19
    },
    {
      "date": "2023-09-10",
      "value": 43
    },
    {
      "date": "2023-09-11",
      "value": 21
    },
    {
      "date": "2023-09-12",
      "value": 44
    },
    {
      "date": "2023-09-13",
      "value": 41
    }
  ]
}