{
  "lastUpdated": "2025-07-23T00:00:46.874Z",
  "stats": {
    "users": {
      "count": 45521,
      "change": -2.8
    },
    "revenue": {
      "amount": 235655,
      "change": 10.4
    },
    "projects": {
      "count": 358,
      "change": -1.5
    },
    "tasks": {
      "count": 2288,
      "change": 15.1
    }
  },
  "activities": [
    {
      "type": "message",
      "title": "System alert",
      "timestamp": "2025-07-23T00:00:46.874Z"
    },
    {
      "type": "project",
      "title": "Task completed",
      "timestamp": "2025-07-22T00:00:30.035Z"
    },
    {
      "type": "project",
      "title": "Project milestone reached",
      "timestamp": "2025-07-21T00:00:26.030Z"
    },
    {
      "type": "message",
      "title": "Project milestone reached",
      "timestamp": "2025-07-20T00:00:59.940Z"
    },
    {
      "type": "payment",
      "title": "Payment received",
      "timestamp": "2025-07-19T00:00:50.831Z"
    }
  ],
  "weeklyActivity": [
    {
      "day": "Mon",
      "value": 14
    },
    {
      "day": "Tue",
      "value": 44
    },
    {
      "day": "Wed",
      "value": 93
    },
    {
      "day": "Thu",
      "value": 14
    },
    {
      "day": "Fri",
      "value": 100
    },
    {
      "day": "Sat",
      "value": 81
    },
    {
      "day": "Sun",
      "value": 39
    }
  ],
  "performanceMetrics": [
    {
      "date": "2023-10-13",
      "value": 47
    },
    {
      "date": "2023-10-14",
      "value": 34
    },
    {
      "date": "2023-10-15",
      "value": 10
    },
    {
      "date": "2023-10-16",
      "value": 26
    },
    {
      "date": "2023-10-17",
      "value": 49
    },
    {
      "date": "2023-10-18",
      "value": 48
    },
    {
      "date": "2023-10-19",
      "value": 43
    }
  ]
}